{
  "/_global-error/page": "app/_global-error/page.js",
  "/_not-found/page": "app/_not-found/page.js",
  "/api/auth/equipos/route": "app/api/auth/equipos/route.js",
  "/api/auth/login/route": "app/api/auth/login/route.js",
  "/api/auth/registro/route": "app/api/auth/registro/route.js",
  "/api/auth/unirse/route": "app/api/auth/unirse/route.js",
  "/api/onboarding/altura/route": "app/api/onboarding/altura/route.js",
  "/api/onboarding/edad/route": "app/api/onboarding/edad/route.js",
  "/api/onboarding/final/route": "app/api/onboarding/final/route.js",
  "/api/onboarding/genero/route": "app/api/onboarding/genero/route.js",
  "/api/onboarding/nombre/route": "app/api/onboarding/nombre/route.js",
  "/api/onboarding/peso/route": "app/api/onboarding/peso/route.js",
  "/equipos/page": "app/equipos/page.js",
  "/favicon.ico/route": "app/favicon.ico/route.js",
  "/login/page": "app/login/page.js",
  "/onboarding/altura/page": "app/onboarding/altura/page.js",
  "/onboarding/edad/page": "app/onboarding/edad/page.js",
  "/onboarding/final/page": "app/onboarding/final/page.js",
  "/onboarding/genero/page": "app/onboarding/genero/page.js",
  "/onboarding/nombre/page": "app/onboarding/nombre/page.js",
  "/onboarding/peso/page": "app/onboarding/peso/page.js",
  "/page": "app/page.js",
  "/registro/page": "app/registro/page.js",
  "/unirse/page": "app/unirse/page.js"
}